joaopedross_csv_converter/__init__.py
joaopedross_csv_converter/converter.py
joaopedross_csv_converter-0.1.1.dist-info/entry_points.txt
joaopedross_csv_converter-0.1.1.dist-info/WHEEL
joaopedross_csv_converter-0.1.1.dist-info/METADATA
joaopedross_csv_converter-0.1.1.dist-info/RECORD
