Metadata-Version: 2.1
Name: joaopedross-csv-converter
Version: 0.1.1
Summary: Converter CSV para JSON e JSON para CSV.
Author: João Pedro
Author-email: joaopedr0ss1697@gmail.com
Requires-Python: >=3.8,<4.0
Classifier: Programming Language :: Python :: 3
Classifier: Programming Language :: Python :: 3.10
Classifier: Programming Language :: Python :: 3.8
Classifier: Programming Language :: Python :: 3.9
Requires-Dist: click (>=8.0.3,<9.0.0)
Requires-Dist: pandas (>=1.3.4,<2.0.0)
